[
    {
        "host": "msfwifi.3g.qq.com",
        "port": 8080
    },
    {
        "host": "14.22.9.53",
        "port": 443
    },
    {
        "host": "183.47.98.11",
        "port": 443
    },
    {
        "host": "183.47.98.25",
        "port": 8080
    },
    {
        "host": "123.151.54.197",
        "port": 8080
    },
    {
        "host": "123.151.54.38",
        "port": 80
    },
    {
        "host": "117.62.243.229",
        "port": 80
    },
    {
        "host": "180.102.191.69",
        "port": 14000
    }
]